config/__init__.py
config/settings.toml
url_revive/.secrets.toml
url_revive/__init__.py
url_revive/archive_reader.py
url_revive/cli_parser.py
url_revive/config.py
url_revive/main.py
url_revive/networking.py
url_revive-0.1.1.dist-info/LICENSE
url_revive-0.1.1.dist-info/METADATA
url_revive-0.1.1.dist-info/WHEEL
url_revive-0.1.1.dist-info/entry_points.txt
url_revive-0.1.1.dist-info/RECORD
