Metadata-Version: 2.3
Name: url-revive
Version: 0.1.1
Summary: Bring those dead links back to life
Author: Raymond Van Wart
Requires-Python: >=3.13,<4.0
Classifier: Programming Language :: Python :: 3
Classifier: Programming Language :: Python :: 3.13
Requires-Dist: colorama (>=0.4.6,<0.5.0)
Requires-Dist: colorlog (>=6.9.0,<7.0.0)
Requires-Dist: dynaconf (>=3.2.10,<4.0.0)
Requires-Dist: multipledispatch (>=1.0.0,<2.0.0)
Requires-Dist: pyrate-limiter (>=3.7.0,<4.0.0)
Requires-Dist: ratelimit (>=2.2.1,<3.0.0)
Requires-Dist: requests (>=2.32.3,<3.0.0)
